gym_pikachu_volleyball/__init__.py
gym_pikachu_volleyball/envs/__init__.py
gym_pikachu_volleyball/envs/pikachu_volleyball.py
gym_pikachu_volleyball/envs/viewer.py
gym_pikachu_volleyball/envs/sprites/ball_0.png
gym_pikachu_volleyball/envs/sprites/ball_1.png
gym_pikachu_volleyball/envs/sprites/ball_2.png
gym_pikachu_volleyball/envs/sprites/ball_3.png
gym_pikachu_volleyball/envs/sprites/ball_4.png
gym_pikachu_volleyball/envs/sprites/ball_hyper.png
gym_pikachu_volleyball/envs/sprites/ball_punch.png
gym_pikachu_volleyball/envs/sprites/ball_trail.png
gym_pikachu_volleyball/envs/sprites/ground_line.png
gym_pikachu_volleyball/envs/sprites/ground_line_leftmost.png
gym_pikachu_volleyball/envs/sprites/ground_line_rightmost.png
gym_pikachu_volleyball/envs/sprites/ground_red.png
gym_pikachu_volleyball/envs/sprites/ground_yellow.png
gym_pikachu_volleyball/envs/sprites/mountain.png
gym_pikachu_volleyball/envs/sprites/net_pillar.png
gym_pikachu_volleyball/envs/sprites/net_pillar_top.png
gym_pikachu_volleyball/envs/sprites/pika_0_0.png
gym_pikachu_volleyball/envs/sprites/pika_0_1.png
gym_pikachu_volleyball/envs/sprites/pika_0_2.png
gym_pikachu_volleyball/envs/sprites/pika_0_3.png
gym_pikachu_volleyball/envs/sprites/pika_0_4.png
gym_pikachu_volleyball/envs/sprites/pika_1_0.png
gym_pikachu_volleyball/envs/sprites/pika_1_1.png
gym_pikachu_volleyball/envs/sprites/pika_1_2.png
gym_pikachu_volleyball/envs/sprites/pika_1_3.png
gym_pikachu_volleyball/envs/sprites/pika_1_4.png
gym_pikachu_volleyball/envs/sprites/pika_2_0.png
gym_pikachu_volleyball/envs/sprites/pika_2_1.png
gym_pikachu_volleyball/envs/sprites/pika_2_2.png
gym_pikachu_volleyball/envs/sprites/pika_2_3.png
gym_pikachu_volleyball/envs/sprites/pika_2_4.png
gym_pikachu_volleyball/envs/sprites/pika_3_0.png
gym_pikachu_volleyball/envs/sprites/pika_3_1.png
gym_pikachu_volleyball/envs/sprites/pika_4_0.png
gym_pikachu_volleyball/envs/sprites/pika_5_0.png
gym_pikachu_volleyball/envs/sprites/pika_5_1.png
gym_pikachu_volleyball-0.0.6.dist-info/METADATA
gym_pikachu_volleyball-0.0.6.dist-info/WHEEL
gym_pikachu_volleyball-0.0.6.dist-info/top_level.txt
gym_pikachu_volleyball-0.0.6.dist-info/RECORD
