Metadata-Version: 2.1
Name: gym-pikachu-volleyball
Version: 0.0.6
Summary: An openai-gym wrapper for pikachu-volleyball
Home-page: https://github.com/MrHoseongLee/gym-pikachu-volleyball
Author: Hoseong Lee
Author-email: mr.hoseong.lee@gmail.com
License: UNKNOWN
Platform: UNKNOWN
Requires-Dist: gym
